{
  "model": "htdemucs",
  "stems": [
    "vocals",
    "no_vocals"
  ],
  "sampling_strategy": "3 x 5-minute chunks (start, middle, end) of 75-minute video",
  "chunks": {
    "chunk-00": {
      "time_range": "0:00 - 5:00 (opening/hook)",
      "duration_s": 300.04,
      "vocals": {
        "integrated_lufs": -22.15,
        "true_peak_dbtp": -3.98,
        "loudness_range_lu": 3.8,
        "narration_pct": 99.4,
        "silence_gaps": 3,
        "total_silence_s": 1.77
      },
      "no_vocals": {
        "integrated_lufs": -36.57,
        "true_peak_dbtp": -9.1,
        "loudness_range_lu": 25.3
      },
      "vocals_to_music_gap_db": 14.42
    },
    "chunk-mid": {
      "time_range": "~37:30 - 42:30 (middle body)",
      "duration_s": 300.04,
      "vocals": {
        "integrated_lufs": -27.03,
        "true_peak_dbtp": -9.3,
        "loudness_range_lu": 3.6,
        "narration_pct": 97.7,
        "silence_gaps": 8,
        "total_silence_s": 6.83
      },
      "no_vocals": {
        "integrated_lufs": -36.6,
        "true_peak_dbtp": -16.54,
        "loudness_range_lu": 15.1
      },
      "vocals_to_music_gap_db": 9.57
    },
    "chunk-end": {
      "time_range": "~69:44 - 75:00 (finale/outro)",
      "duration_s": 316.03,
      "vocals": {
        "integrated_lufs": -26.95,
        "true_peak_dbtp": -7.36,
        "loudness_range_lu": 4.1,
        "narration_pct": 98.7,
        "silence_gaps": 7,
        "total_silence_s": 4.18
      },
      "no_vocals": {
        "integrated_lufs": -60.97,
        "true_peak_dbtp": -29.13,
        "loudness_range_lu": 6.9
      },
      "vocals_to_music_gap_db": 34.02
    }
  },
  "patterns": {
    "vocal_consistency": "Tight LRA across all chunks (3.6-4.1 LU) indicates heavily compressed/consistent narration",
    "opening_louder": "Opening vocals are ~5 dB louder than body/end (energetic hook)",
    "music_dynamic_range": "Music has wide dynamic range in opening (25.3 LU), moderate in middle (15.1 LU), narrow at end (6.9 LU)",
    "music_energy_opening": "Opening has loudest music with distinct peaks (anime clips / action scenes)",
    "music_energy_end": "End section has minimal music - narration dominant, suggesting reflective/conclusion mode",
    "narration_density": "97.7-99.4% narration coverage - nearly zero dead air",
    "vocal_music_gap": "Opening: 14.4 dB, Middle: 9.6 dB, End: 34.0 dB gap between vocals and music"
  }
}